emgregs/__init__.py
emgregs/emg_reg.py
emgregs/flare_reg.py
emgregs/simulation.py
emgregs-0.0.7.dist-info/LICENSE
emgregs-0.0.7.dist-info/METADATA
emgregs-0.0.7.dist-info/WHEEL
emgregs-0.0.7.dist-info/RECORD
